LICENSE
README.md
setup.cfg
setup.py
screwdriver_cd_sdk_python/__init__.py
screwdriver_cd_sdk_python/events.py
screwdriver_cd_sdk_python/pipeline.py
screwdriver_cd_sdk_python/screwdriver_initializer.py
screwdriver_cd_sdk_python/secrets.py
screwdriver_cd_sdk_python.egg-info/PKG-INFO
screwdriver_cd_sdk_python.egg-info/SOURCES.txt
screwdriver_cd_sdk_python.egg-info/dependency_links.txt
screwdriver_cd_sdk_python.egg-info/not-zip-safe
screwdriver_cd_sdk_python.egg-info/top_level.txt