Metadata-Version: 2.1
Name: screwdriver-cd-sdk-python
Version: 1.0.1
Summary: Screwdriver CD Python Software Development Kit (SDK) for managing resources in Screwdriver
Home-page: https://github.com/paion-data/screwdriver-cd-sdk-python
Author: Paion Data
Author-email: jack20220723@gmail.com
License: Apache-2.0
Requires-Python: >=3.10
License-File: LICENSE
